midist-0.2.3.dist-info/METADATA
midist-0.2.3.dist-info/WHEEL
midist-0.2.3.dist-info/entry_points.txt
midist-0.2.3.dist-info/licenses/LICENSE
midist/__init__.py
midist/cli.py
midist/generate.py
midist-0.2.3.dist-info/RECORD
