Metadata-Version: 2.1
Name: midist
Version: 0.2.3
Summary: Command line tool for easy access to Misskey's theme/plugin installation functionality.
Author-Email: AmaseCocoa <amase.cocoa@gmail.com>
License: MIT
Project-URL: Repository, https://github.com/AmaseCocoa/midist
Requires-Python: >=3.9
Requires-Dist: typer>=0.13.1
Requires-Dist: jinja2>=3.1.4
